LICENSE-APACHE
LICENSE-MIT
MANIFEST.in
README.rst
setup.py
luxinema/__init__.py
luxinema/luxinema.py
luxinema/utils.py
luxinema.egg-info/PKG-INFO
luxinema.egg-info/SOURCES.txt
luxinema.egg-info/dependency_links.txt
luxinema.egg-info/entry_points.txt
luxinema.egg-info/requires.txt
luxinema.egg-info/top_level.txt
tests/__init__.py
tests/tests.py