Metadata-Version: 1.1
Name: luxinema
Version: 0.1.2
Summary: Retrieve cinema information for the LUX Nijmegen
Home-page: https://github.com/dangom/luxinema
Author: Daniel Gomez
Author-email: d.gomez@posteo.org
License: MIT/Apache-2.0
Keywords: cinema
Platform: UNKNOWN
Classifier: Development Status :: 4 - Beta
Classifier: Intended Audience :: Developers
Classifier: Environment :: Console
Classifier: License :: OSI Approved :: MIT License
Classifier: License :: OSI Approved :: Apache Software License
Classifier: Natural Language :: English
Classifier: Programming Language :: Python :: 3.5
Classifier: Programming Language :: Python :: 3.6
Classifier: Programming Language :: Python :: Implementation :: CPython
Classifier: Programming Language :: Python :: Implementation :: PyPy
